rtairegulatory/__init__.py
rtairegulatory/__main__.py
rtairegulatory/_build.py
rtairegulatory-0.1.16.dist-info/entry_points.txt
rtairegulatory-0.1.16.dist-info/LICENSE
rtairegulatory-0.1.16.dist-info/WHEEL
rtairegulatory-0.1.16.dist-info/METADATA
rtairegulatory-0.1.16.dist-info/RECORD
